{
  "bcd_calculation_version": "BCD-INDEPENDENT-V1",
  "bcd_data_completeness": 0.1429,
  "bcd_missing_components": [
    "main7_returns",
    "main7_weights",
    "main7_concentration",
    "sector_breadth",
    "sector_diffusion",
    "otc_return_pct",
    "small_mid_breadth",
    "small_mid_weakness",
    "turnover_concentration_topn",
    "turnover_concentration"
  ],
  "bcd_source_dependencies": [
    "advancing_issues<-breadth_csv",
    "declining_issues<-breadth_csv",
    "breadth_history<-bcd_feature_builder",
    "taiex_return_pct<-taiex_price"
  ],
  "bcd_status": "INCOMPLETE",
  "component_scores": {
    "index_breadth_divergence": 0.0
  },
  "coverage": {
    "available_components": 3,
    "coverage_ratio": 0.25,
    "coverage_status": "INCOMPLETE",
    "mapping_table": [
      {
        "component": "Index Breadth Divergence",
        "current_availability": "AVAILABLE",
        "missing_inputs": [],
        "provider": "taiex_price + breadth_csv + bcd_feature_builder",
        "required_inputs": [
          "taiex_return_pct",
          "advancing_issues",
          "declining_issues",
          "breadth_history"
        ]
      },
      {
        "component": "Index Breadth Current",
        "current_availability": "AVAILABLE",
        "missing_inputs": [],
        "provider": "breadth_csv",
        "required_inputs": [
          "advancing_issues",
          "declining_issues"
        ]
      },
      {
        "component": "Index Breadth History",
        "current_availability": "AVAILABLE",
        "missing_inputs": [],
        "provider": "bcd_feature_builder",
        "required_inputs": [
          "breadth_history"
        ]
      },
      {
        "component": "Main7 Returns",
        "current_availability": "MISSING",
        "missing_inputs": [
          "main7_returns"
        ],
        "provider": "leadership_csv",
        "required_inputs": [
          "main7_returns"
        ]
      },
      {
        "component": "Main7 Weights",
        "current_availability": "MISSING",
        "missing_inputs": [
          "main7_weights"
        ],
        "provider": "leadership_csv",
        "required_inputs": [
          "main7_weights"
        ]
      },
      {
        "component": "Main7 Concentration",
        "current_availability": "MISSING",
        "missing_inputs": [
          "main7_returns",
          "main7_weights"
        ],
        "provider": "leadership_csv",
        "required_inputs": [
          "main7_returns",
          "main7_weights"
        ]
      },
      {
        "component": "Sector Breadth",
        "current_availability": "MISSING",
        "missing_inputs": [
          "sector_returns",
          "sector_above_ma20"
        ],
        "provider": "sector_breadth_csv",
        "required_inputs": [
          "sector_returns",
          "sector_above_ma20"
        ]
      },
      {
        "component": "Sector Diffusion",
        "current_availability": "MISSING",
        "missing_inputs": [
          "sector_returns",
          "sector_above_ma20"
        ],
        "provider": "sector_breadth_csv",
        "required_inputs": [
          "sector_returns",
          "sector_above_ma20"
        ]
      },
      {
        "component": "OTC Return",
        "current_availability": "MISSING",
        "missing_inputs": [
          "otc_return_pct"
        ],
        "provider": "otc_csv",
        "required_inputs": [
          "otc_return_pct"
        ]
      },
      {
        "component": "Small/Mid Breadth",
        "current_availability": "MISSING",
        "missing_inputs": [
          "small_mid_breadth"
        ],
        "provider": "small_mid_breadth_csv",
        "required_inputs": [
          "small_mid_breadth"
        ]
      },
      {
        "component": "Small/Mid Weakness",
        "current_availability": "MISSING",
        "missing_inputs": [
          "small_mid_breadth",
          "otc_return_pct"
        ],
        "provider": "small_mid_breadth_csv + otc_csv",
        "required_inputs": [
          "small_mid_breadth",
          "otc_return_pct"
        ]
      },
      {
        "component": "Turnover Concentration",
        "current_availability": "MISSING",
        "missing_inputs": [
          "turnover_concentration_topn"
        ],
        "provider": "turnover_csv",
        "required_inputs": [
          "turnover_concentration_topn"
        ]
      }
    ],
    "reason": "9 components unavailable",
    "total_components": 12,
    "unavailable_components": [
      "Main7 Returns",
      "Main7 Weights",
      "Main7 Concentration",
      "Sector Breadth",
      "Sector Diffusion",
      "OTC Return",
      "Small/Mid Breadth",
      "Small/Mid Weakness",
      "Turnover Concentration"
    ]
  },
  "data_quality_status": "INCOMPLETE",
  "final_score": null,
  "missing_components": [
    "main7_returns",
    "main7_weights",
    "main7_concentration",
    "sector_breadth",
    "sector_diffusion",
    "otc_return_pct",
    "small_mid_breadth",
    "small_mid_weakness",
    "turnover_concentration_topn",
    "turnover_concentration"
  ],
  "raw_inputs": {
    "advancing_issues": 9333,
    "breadth_history": [
      {
        "advancing_issues": 620,
        "declining_issues": 340,
        "taiex_return_pct": 0.42,
        "trade_date": "2026-06-03"
      },
      {
        "advancing_issues": 3144,
        "declining_issues": 9578,
        "taiex_return_pct": -1.3278321517877676,
        "trade_date": "2026-06-05"
      },
      {
        "advancing_issues": 9333,
        "declining_issues": 2154,
        "taiex_return_pct": 2.3629032669238543,
        "trade_date": "2026-06-12"
      }
    ],
    "coverage": {
      "available_components": 3,
      "coverage_ratio": 0.25,
      "coverage_status": "INCOMPLETE",
      "mapping_table": [
        {
          "component": "Index Breadth Divergence",
          "current_availability": "AVAILABLE",
          "missing_inputs": [],
          "provider": "taiex_price + breadth_csv + bcd_feature_builder",
          "required_inputs": [
            "taiex_return_pct",
            "advancing_issues",
            "declining_issues",
            "breadth_history"
          ]
        },
        {
          "component": "Index Breadth Current",
          "current_availability": "AVAILABLE",
          "missing_inputs": [],
          "provider": "breadth_csv",
          "required_inputs": [
            "advancing_issues",
            "declining_issues"
          ]
        },
        {
          "component": "Index Breadth History",
          "current_availability": "AVAILABLE",
          "missing_inputs": [],
          "provider": "bcd_feature_builder",
          "required_inputs": [
            "breadth_history"
          ]
        },
        {
          "component": "Main7 Returns",
          "current_availability": "MISSING",
          "missing_inputs": [
            "main7_returns"
          ],
          "provider": "leadership_csv",
          "required_inputs": [
            "main7_returns"
          ]
        },
        {
          "component": "Main7 Weights",
          "current_availability": "MISSING",
          "missing_inputs": [
            "main7_weights"
          ],
          "provider": "leadership_csv",
          "required_inputs": [
            "main7_weights"
          ]
        },
        {
          "component": "Main7 Concentration",
          "current_availability": "MISSING",
          "missing_inputs": [
            "main7_returns",
            "main7_weights"
          ],
          "provider": "leadership_csv",
          "required_inputs": [
            "main7_returns",
            "main7_weights"
          ]
        },
        {
          "component": "Sector Breadth",
          "current_availability": "MISSING",
          "missing_inputs": [
            "sector_returns",
            "sector_above_ma20"
          ],
          "provider": "sector_breadth_csv",
          "required_inputs": [
            "sector_returns",
            "sector_above_ma20"
          ]
        },
        {
          "component": "Sector Diffusion",
          "current_availability": "MISSING",
          "missing_inputs": [
            "sector_returns",
            "sector_above_ma20"
          ],
          "provider": "sector_breadth_csv",
          "required_inputs": [
            "sector_returns",
            "sector_above_ma20"
          ]
        },
        {
          "component": "OTC Return",
          "current_availability": "MISSING",
          "missing_inputs": [
            "otc_return_pct"
          ],
          "provider": "otc_csv",
          "required_inputs": [
            "otc_return_pct"
          ]
        },
        {
          "component": "Small/Mid Breadth",
          "current_availability": "MISSING",
          "missing_inputs": [
            "small_mid_breadth"
          ],
          "provider": "small_mid_breadth_csv",
          "required_inputs": [
            "small_mid_breadth"
          ]
        },
        {
          "component": "Small/Mid Weakness",
          "current_availability": "MISSING",
          "missing_inputs": [
            "small_mid_breadth",
            "otc_return_pct"
          ],
          "provider": "small_mid_breadth_csv + otc_csv",
          "required_inputs": [
            "small_mid_breadth",
            "otc_return_pct"
          ]
        },
        {
          "component": "Turnover Concentration",
          "current_availability": "MISSING",
          "missing_inputs": [
            "turnover_concentration_topn"
          ],
          "provider": "turnover_csv",
          "required_inputs": [
            "turnover_concentration_topn"
          ]
        }
      ],
      "reason": "9 components unavailable",
      "total_components": 12,
      "unavailable_components": [
        "Main7 Returns",
        "Main7 Weights",
        "Main7 Concentration",
        "Sector Breadth",
        "Sector Diffusion",
        "OTC Return",
        "Small/Mid Breadth",
        "Small/Mid Weakness",
        "Turnover Concentration"
      ]
    },
    "declining_issues": 2154,
    "main7_closes": null,
    "main7_previous_closes": null,
    "main7_returns": {},
    "main7_turnover_amounts": null,
    "main7_weights": {},
    "otc_return_pct": null,
    "sector_above_ma20": {},
    "sector_returns": {},
    "small_mid_breadth": null,
    "taiex_return_pct": 2.3629032669238543,
    "turnover_concentration_topn": null
  },
  "source_fields": {
    "advancing_issues": "breadth_csv",
    "breadth_history": "bcd_feature_builder",
    "breadth_weakens_for_2_days": "breadth_csv",
    "close": "taiex_price",
    "close_below_ma20_consecutive_days": "taiex_price",
    "count_main_7_below_ma20": "leadership_csv",
    "count_main_7_below_ma60": "leadership_csv",
    "declining_gt_advancing_consecutive_days": "breadth_csv",
    "declining_issues": "breadth_csv",
    "declining_issues_significantly_expand": "breadth_csv",
    "declining_issues_significantly_gt_advancing": "breadth_csv",
    "foreign_large_sell": "foreign_flow_csv",
    "foreign_spot_large_sell": "foreign_flow_csv",
    "foreign_spot_net_buy": "foreign_flow_csv",
    "foreign_spot_net_sell": "foreign_flow_csv",
    "foreign_spot_net_sell_consecutive_days": "foreign_flow_csv",
    "futures_hedging_increases": "futures_csv",
    "futures_hedging_significant": "futures_csv",
    "futures_net_short_decreases": "futures_csv",
    "futures_net_short_increases": "futures_csv",
    "hot_stock_margin_fast_increase": "margin_csv",
    "index_5d_return_pct": "taiex_price",
    "index_down": "breadth_csv",
    "ma20": "taiex_price",
    "ma20_slope": "taiex_price",
    "ma5": "taiex_price",
    "ma60": "taiex_price",
    "main7_closes": "margin_csv",
    "main7_previous_closes": "margin_csv",
    "main7_turnover_amounts": "margin_csv",
    "main_7_below_ma20_symbols": "leadership_csv",
    "main_7_symbols": "leadership_csv",
    "majority_main_7_assets_above_ma20": "leadership_csv",
    "margin_balance_5d_decline_pct": "margin_csv",
    "margin_balance_5d_flat_or_down": "margin_csv",
    "margin_balance_5d_increases": "margin_csv",
    "margin_not_retreating": "margin_csv",
    "mhs": "leadership_csv",
    "observed_at": "margin_csv",
    "one_day_return_pct": "taiex_price",
    "pcr_rises": "options_csv",
    "pcr_stable": "options_csv",
    "previous_ma60": "taiex_price",
    "return_60d_pct": "taiex_price",
    "taiex_return_pct": "taiex_price",
    "tail_risk": "options_csv",
    "turnover_amount": "taiex_price",
    "twd_appreciates": "fx_csv",
    "twd_depreciates_significantly": "fx_csv",
    "twd_stable": "fx_csv",
    "two_day_return_pct": "taiex_price",
    "usd_twd_3d_change_pct": "fx_csv",
    "usd_twd_5d_change_pct": "fx_csv",
    "vix_rises": "options_csv",
    "vix_stable": "options_csv"
  },
  "threshold_hits": {
    "index_breadth_divergence.advancing_ratio_below_45pct": false,
    "index_breadth_divergence.below_history_mean_10pp": false,
    "index_breadth_divergence.decliners_gt_advancers": false,
    "index_breadth_divergence.taiex_up": true
  }
}
