{
  "breadth": {
    "advancing_issues": "advancing_issues",
    "breadth_weakens_for_2_days": "breadth_weakens_for_2_days",
    "date": "observed_at",
    "declining_issues": "declining_issues",
    "declining_issues_significantly_gt_advancing": "declining_issues_significantly_gt_advancing",
    "index_down": "index_down"
  },
  "foreign_flow": {
    "date": "observed_at",
    "foreign_large_sell": "foreign_large_sell",
    "foreign_spot_net_sell_consecutive_days": "foreign_spot_net_sell_consecutive_days",
    "futures_hedging_increases": "futures_hedging_increases"
  },
  "fx": {
    "date": "observed_at",
    "usd_twd": "usd_twd",
    "usd_twd_3d_change_pct": "usd_twd_3d_change_pct",
    "usd_twd_5d_change_pct": "usd_twd_5d_change_pct"
  },
  "leadership": {
    "count_main_7_below_ma20": "count_main_7_below_ma20",
    "date": "observed_at",
    "main_7_below_ma20_symbols": "main_7_below_ma20_symbols",
    "main_7_symbols": "main_7_symbols"
  },
  "price": {
    "date": "observed_at",
    "taiex_close": "close",
    "taiex_ma20": "ma20",
    "taiex_ma20_slope": "ma20_slope",
    "taiex_ma5": "ma5",
    "taiex_ma60": "ma60",
    "turnover_amount": "turnover_amount"
  },
  "scores": {
    "date": "observed_at",
    "mhs": "mhs",
    "tail_risk": "tail_risk"
  }
}
